magellan/env_interrogation.py
magellan/package_interrogation.py
magellan/reports.py
magellan/_version.py
magellan/package_utils.py
magellan/__init__.py
magellan/main.py
magellan/env_utils.py
magellan/code.py
magellan/utils.py
magellan/deps_utils.py
magellan/cmd.py
magellan/analysis.py
magellan/data/tmpVexRC
magellan-1.0.0b0.dist-info/metadata.json
magellan-1.0.0b0.dist-info/top_level.txt
magellan-1.0.0b0.dist-info/entry_points.txt
magellan-1.0.0b0.dist-info/RECORD
magellan-1.0.0b0.dist-info/METADATA
magellan-1.0.0b0.dist-info/pbr.json
magellan-1.0.0b0.dist-info/WHEEL
magellan-1.0.0b0.dist-info/DESCRIPTION.rst
