Metadata-Version: 2.0
Name: magellan
Version: 1.0.0b0
Summary: Explore python packages like your name is Fernando.
Home-page: https://github.com/Maplecroft/Magellan/
Author: AJ De-Gol
Author-email: anthony.de-gol@maplecroft.com
License: MIT
Keywords: package management conflict detection
Platform: UNKNOWN
Classifier: Development Status :: 4 - Beta
Classifier: Intended Audience :: Developers
Classifier: Natural Language :: English
Classifier: License :: OSI Approved :: MIT License
Classifier: Operating System :: POSIX :: Linux
Classifier: Programming Language :: Python :: 2.7
Classifier: Programming Language :: Python :: 3.4
Classifier: Topic :: Software Development :: Quality Assurance
Classifier: Topic :: Utilities
Requires-Dist: setuptools (>=17.1)
Requires-Dist: yarg
Requires-Dist: virtualenv
Requires-Dist: vex
Requires-Dist: argparse
Requires-Dist: terminaltables
Requires-Dist: colorclass
Requires-Dist: natsort (>=4.0.0)
Requires-Dist: pip (==6.1.1)
